[{"fromUserID": "lameei", "toUserID": "mtz"}, {"fromUserID": "lameei", "toUserID": "davoodtr"}, {"fromUserID": "lameei", "toUserID": "arashqu1ckz"}, {"fromUserID": "lameei", "toUserID": "hajjehforoosh"}, {"fromUserID": "lameei", "toUserID": "mimalef70"}, {"fromUserID": "lameei", "toUserID": "mjnanakar"}, {"fromUserID": "lameei", "toUserID": "mahdiabbasi58"}, {"fromUserID": "lameei", "toUserID": "nasrabadi"}, {"fromUserID": "lameei", "toUserID": "nazaninfarahani"}, {"fromUserID": "lameei", "toUserID": "RahimHashemi"}, {"fromUserID": "lameei", "toUserID": "mzargarpour"}, {"fromUserID": "lameei", "toUserID": "Farbod.digital"}, {"fromUserID": "lameei", "toUserID": "ehsantarighat"}, {"fromUserID": "lameei", "toUserID": "ghenaat"}, {"fromUserID": "lameei", "toUserID": "ardeshir"}, {"fromUserID": "lameei", "toUserID": "badiezadeh"}, {"fromUserID": "lameei", "toUserID": "negartash"}, {"fromUserID": "lameei", "toUserID": "RVahidian"}, {"fromUserID": "lameei", "toUserID": "islamizad"}, {"fromUserID": "lameei", "toUserID": "adeltalebi"}, {"fromUserID": "lameei", "toUserID": "jadijadi"}, {"fromUserID": "lameei", "toUserID": "ali.khaleghian"}, {"fromUserID": "lameei", "toUserID": "atakhalighi"}, {"fromUserID": "lameei", "toUserID": "pasargadtabac"}, {"fromUserID": "lameei", "toUserID": "kheyzaran"}, {"fromUserID": "lameei", "toUserID": "nafariehamir"}, {"fromUserID": "lameei", "toUserID": "amir.mehrani"}, {"fromUserID": "lameei", "toUserID": "a3dho3yn"}, {"fromUserID": "lameei", "toUserID": "niloufarmousavi"}, {"fromUserID": "lameei", "toUserID": "yasaman.rj"}, {"fromUserID": "lameei", "toUserID": "eterfanet"}, {"fromUserID": "lameei", "toUserID": "behnaz.mohammadi87"}, {"fromUserID": "lameei", "toUserID": "i.davoodian"}, {"fromUserID": "lameei", "toUserID": "reza.heidari"}, {"fromUserID": "lameei", "toUserID": "hadi.nili"}]